secmind/__init__.py
secmind/example/__init__.py
secmind/example/connector_panabit_ntc_r1.py
secmind/rpa/__init__.py
secmind/rpa_v2/__init__.py
secmind/rpa_v2/analysis/DetectionAsset.py
secmind/rpa_v2/analysis/__init__.py
secmind/rpa_v2/analysis/hunt_DaMeng.py
secmind/rpa_v2/analysis/hunt_kunDB.py
secmind/rpa_v2/analysis/hunt_linux.py
secmind/rpa_v2/analysis/hunt_mysql.py
secmind/rpa_v2/analysis/hunt_oracle.py
secmind/rpa_v2/analysis/hunt_sqlserver.py
secmind/rpa_v2/analysis/hunt_windows.py
secmind/rpa_v2/analysis/hunt_windowsAD_thread.py
secmind/rpa_v2/entity/__init__.py
secmind/rpa_v2/entity/exception_enum.py
secmind/rpa_v2/entity/task_execution_result.py
secmind/rpa_v2/samba/__init__.py
secmind/rpa_v2/samba/samba_wrapper.py
secmind/rpa_v2/selenium/__init__.py
secmind/rpa_v2/selenium/chrome_driver_manager.py
secmind/rpa_v2/selenium/selenium_general_verify.py
secmind/rpa_v2/selenium/selenium_wrapper.py
secmind/rpa_v2/ssh/__init__.py
secmind/rpa_v2/ssh/ssh_wrapper.py
secmind/rpa_v2/telnet/__init__.py
secmind/rpa_v2/telnet/telnet_wrapper.py
secmind/rpa_v2/utils/__init__.py
secmind/rpa_v2/utils/captcha.py
secmind/rpa_v2/utils/common.py
secmind/rpa_v2/utils/exception_utils.py
secmind/rpa_v2/utils/invoke.py
secmind/rpa_v2/utils/log.py
secmind/rpa_v2/winrm/__init__.py
secmind/rpa_v2/winrm/winrm_wrapper.py
secmind/rpa_v2_sample/__init__.py
secmind/rpa_v2_sample/samba/__init__.py
secmind/rpa_v2_sample/samba/sample_samba_get_users.py
secmind/rpa_v2_sample/samba/sample_samba_mod_pwd.py
secmind/rpa_v2_sample/samba/sample_samba_verify.py
secmind/rpa_v2_sample/selenium/__init__.py
secmind/rpa_v2_sample/selenium/sample_general.py
secmind/rpa_v2_sample/selenium/sample_general_verify.py
secmind/rpa_v2_sample/ssh/__init__.py
secmind/rpa_v2_sample/ssh/sample_ssh_get_users.py
secmind/rpa_v2_sample/ssh/sample_ssh_mod_pwd.py
secmind/rpa_v2_sample/ssh/sample_ssh_verify.py
secmind/rpa_v2_sample/telnet/__init__.py
secmind/rpa_v2_sample/telnet/sample_telnet_get_users.py
secmind-1.5.15.dist-info/licenses/LICENSE
secmind-1.5.15.dist-info/METADATA
secmind-1.5.15.dist-info/WHEEL
secmind-1.5.15.dist-info/top_level.txt
secmind-1.5.15.dist-info/RECORD
