Metadata-Version: 2.4
Name: secmind
Version: 1.5.15
Summary: Automation library for xPAM
Home-page: https://github.com/wandoutech
Author: SecMind xPAM
Author-email: service@wandoutech.com
Classifier: Programming Language :: Python :: 3
Classifier: License :: OSI Approved :: Apache Software License
Classifier: Operating System :: OS Independent
Requires-Python: >=3
License-File: LICENSE
Requires-Dist: selenium>=3.141.0
Requires-Dist: paramiko>=3.0.0
Requires-Dist: pywinrm>=0.5.0
Requires-Dist: ddddocr>=1.5.5
Requires-Dist: chardet==4.0.0
Requires-Dist: dill==0.4.0
Dynamic: author
Dynamic: author-email
Dynamic: classifier
Dynamic: description
Dynamic: description-content-type
Dynamic: home-page
Dynamic: license-file
Dynamic: requires-dist
Dynamic: requires-python
Dynamic: summary
